metatron/__init__.py
metatron/metatron.py
metatron/schemas.py
metatron/tests.py
metatron/version.py
metatron-0.5.dist-info/LICENSE.txt
metatron-0.5.dist-info/METADATA
metatron-0.5.dist-info/WHEEL
metatron-0.5.dist-info/top_level.txt
metatron-0.5.dist-info/RECORD
