Metadata-Version: 2.1
Name: metatron
Version: 0.5
Summary: Python 3 HTML meta tag parser, with emphasis on complex meta tag structures with support for OpenGraph and Twitter Card tags, including array handling
Home-page: https://github.com/harel/metatron
Author: Harel Malka
Author-email: harel@harelmalka.com
License: MIT
Download-URL: https://github.com/harel/metatron/archive/0.5.tar.gz
Keywords: html meta parser opengraph twittercard
Platform: UNKNOWN
Classifier: Development Status :: 4 - Beta
Classifier: License :: OSI Approved :: MIT License
Classifier: Intended Audience :: Developers
Classifier: Topic :: Communications :: Email
Classifier: Programming Language :: Python :: 3.5
Requires-Dist: beautifulsoup4
Requires-Dist: requests
